LICENSE.txt
MANIFEST.in
README.rst
setup.py
aadb/__init__.py
auto_adjust_display_brightness.egg-info/PKG-INFO
auto_adjust_display_brightness.egg-info/SOURCES.txt
auto_adjust_display_brightness.egg-info/dependency_links.txt
auto_adjust_display_brightness.egg-info/entry_points.txt
auto_adjust_display_brightness.egg-info/requires.txt
auto_adjust_display_brightness.egg-info/top_level.txt