Metadata-Version: 1.1
Name: auto-adjust-display-brightness
Version: 1.3.1
Summary: Automatically adjust Linux display brightness
Home-page: https://github.com/xolox/python-auto-adjust-display-brightness
Author: Peter Odding
Author-email: peter@peterodding.com
License: UNKNOWN
Platform: UNKNOWN
Classifier: Development Status :: 4 - Beta
Classifier: Environment :: Console
Classifier: Environment :: X11 Applications
Classifier: Intended Audience :: Developers
Classifier: Intended Audience :: Information Technology
Classifier: Intended Audience :: System Administrators
Classifier: License :: OSI Approved :: MIT License
Classifier: Operating System :: POSIX :: Linux
Classifier: Programming Language :: Python :: 2.6
Classifier: Programming Language :: Python :: 2.7
Classifier: Topic :: Desktop Environment
Classifier: Topic :: System :: Systems Administration
Classifier: Topic :: Utilities
